{"id":21,"date":"2020-09-12T17:49:00","date_gmt":"2020-09-12T17:49:00","guid":{"rendered":"http:\/\/localhost\/scione\/?page_id=21"},"modified":"2020-09-12T17:49:31","modified_gmt":"2020-09-12T17:49:31","slug":"search","status":"publish","type":"page","link":"http:\/\/localhost\/scione\/search\/","title":{"rendered":"Search"},"content":{"rendered":"\n<p><\/p>\n\n\n\n<script async src=\"https:\/\/cse.google.com\/cse.js?cx=82d4b556dffc11d6f\"><\/script>\n<div class=\"gcse-search\"><\/div>\n","protected":false},"excerpt":{"rendered":"","protected":false},"author":1,"featured_media":0,"parent":0,"menu_order":0,"comment_status":"closed","ping_status":"closed","template":"","meta":[],"yoast_head":"<!-- This site is optimized with the Yoast SEO plugin v14.9 - https:\/\/yoast.com\/wordpress\/plugins\/seo\/ -->\r\n<title>Search - Scione.io<\/title>\r\n<meta name=\"robots\" content=\"index, follow, max-snippet:-1, max-image-preview:large, max-video-preview:-1\" \/>\r\n<link rel=\"canonical\" href=\"http:\/\/localhost\/scione\/search.html\" \/>\r\n<meta property=\"og:locale\" content=\"en_US\" \/>\r\n<meta property=\"og:type\" content=\"article\" \/>\r\n<meta property=\"og:title\" content=\"Search - Scione.io\" \/>\r\n<meta property=\"og:url\" content=\"http:\/\/localhost\/scione\/search.html\" \/>\r\n<meta property=\"og:site_name\" content=\"Scione.io\" \/>\r\n<meta property=\"article:modified_time\" content=\"2020-09-12T17:49:31+00:00\" \/>\r\n<meta name=\"twitter:card\" content=\"summary_large_image\" \/>\r\n<script type=\"application\/ld+json\" class=\"yoast-schema-graph\">{\r\n\t    \"@context\": \"https:\/\/schema.org\",\r\n\t    \"@graph\": [\r\n\t        {\r\n\t            \"@type\": \"WebSite\",\r\n\t            \"@id\": \"http:\/\/localhost\/scione\/#website\",\r\n\t            \"url\": \"http:\/\/localhost\/scione\/\",\r\n\t            \"name\": \"Scione.io\",\r\n\t            \"description\": \"Just another WordPress site\",\r\n\t            \"potentialAction\": [\r\n\t                {\r\n\t                    \"@type\": \"SearchAction\",\r\n\t                    \"target\": \"http:\/\/localhost\/scione\/?s={search_term_string}\",\r\n\t                    \"query-input\": \"required name=search_term_string\"\r\n\t                }\r\n\t            ],\r\n\t            \"inLanguage\": \"en-US\"\r\n\t        },\r\n\t        {\r\n\t            \"@type\": \"WebPage\",\r\n\t            \"@id\": \"http:\/\/localhost\/scione\/search.html#webpage\",\r\n\t            \"url\": \"http:\/\/localhost\/scione\/search.html\",\r\n\t            \"name\": \"Search - Scione.io\",\r\n\t            \"isPartOf\": {\r\n\t                \"@id\": \"http:\/\/localhost\/scione\/#website\"\r\n\t            },\r\n\t            \"datePublished\": \"2020-09-12T17:49:00+00:00\",\r\n\t            \"dateModified\": \"2020-09-12T17:49:31+00:00\",\r\n\t            \"inLanguage\": \"en-US\",\r\n\t            \"potentialAction\": [\r\n\t                {\r\n\t                    \"@type\": \"ReadAction\",\r\n\t                    \"target\": [\r\n\t                        \"http:\/\/localhost\/scione\/search.html\"\r\n\t                    ]\r\n\t                }\r\n\t            ]\r\n\t        }\r\n\t    ]\r\n\t}<\/script>\r\n<!-- \/ Yoast SEO plugin. -->","amp_validity":null,"amp_enabled":false,"_links":{"self":[{"href":"http:\/\/localhost\/scione\/wp-json\/wp\/v2\/pages\/21"}],"collection":[{"href":"http:\/\/localhost\/scione\/wp-json\/wp\/v2\/pages"}],"about":[{"href":"http:\/\/localhost\/scione\/wp-json\/wp\/v2\/types\/page"}],"author":[{"embeddable":true,"href":"http:\/\/localhost\/scione\/wp-json\/wp\/v2\/users\/1"}],"replies":[{"embeddable":true,"href":"http:\/\/localhost\/scione\/wp-json\/wp\/v2\/comments?post=21"}],"version-history":[{"count":2,"href":"http:\/\/localhost\/scione\/wp-json\/wp\/v2\/pages\/21\/revisions"}],"predecessor-version":[{"id":24,"href":"http:\/\/localhost\/scione\/wp-json\/wp\/v2\/pages\/21\/revisions\/24"}],"wp:attachment":[{"href":"http:\/\/localhost\/scione\/wp-json\/wp\/v2\/media?parent=21"}],"curies":[{"name":"wp","href":"https:\/\/api.w.org\/{rel}","templated":true}]}}